.dockerignore
.editorconfig
.flake8
.gitattributes
.gitignore
CHANGES.rst
CONTRIBUTING.rst
Dockerfile
LICENSE.txt
MANIFEST.in
README.md
appveyor.yml
pyproject.toml
requirements-dev.txt
requirements-setup.txt
requirements.txt
scikit-ci.yml
setup.cfg
setup.py
versioneer.py
.circleci/config.yml
.github/ISSUE_TEMPLATE/bug_report.md
.github/ISSUE_TEMPLATE/feature-extraction-question.md
bin/DatasetHierarchyReader.py
bin/GenerateInputCSV_Datasethierarchy.py
bin/GenerateInputCSV_Filename.py
bin/resampleMask.py
bin/testParams.py
conda/bld.bat
conda/build.sh
conda/configure_conda.bat
conda/configure_conda.sh
conda/meta.yaml
data/README.md
data/brain1_image.nrrd
data/brain1_label.nrrd
data/brain2_image.nrrd
data/brain2_label.nrrd
data/breast1_image.nrrd
data/breast1_label.nrrd
data/lung1_image.nrrd
data/lung1_label.nrrd
data/lung2_image.nrrd
data/lung2_label.nrrd
data/prostate_phantom_subvolume-label.nrrd
data/prostate_phantom_subvolume.nrrd
data/baseline/baseline_firstorder.csv
data/baseline/baseline_glcm.csv
data/baseline/baseline_gldm.csv
data/baseline/baseline_glrlm.csv
data/baseline/baseline_glszm.csv
data/baseline/baseline_ngtdm.csv
data/baseline/baseline_shape.csv
data/baseline/baseline_shape2D.csv
data/baseline/brain1_glcm.npy
data/baseline/brain1_gldm.npy
data/baseline/brain1_glrlm.npy
data/baseline/brain1_glszm.npy
data/baseline/brain1_ngtdm.npy
data/baseline/brain2_glcm.npy
data/baseline/brain2_gldm.npy
data/baseline/brain2_glrlm.npy
data/baseline/brain2_glszm.npy
data/baseline/brain2_ngtdm.npy
data/baseline/breast1_glcm.npy
data/baseline/breast1_gldm.npy
data/baseline/breast1_glrlm.npy
data/baseline/breast1_glszm.npy
data/baseline/breast1_ngtdm.npy
data/baseline/lung1_glcm.npy
data/baseline/lung1_gldm.npy
data/baseline/lung1_glrlm.npy
data/baseline/lung1_glszm.npy
data/baseline/lung1_ngtdm.npy
data/baseline/lung2_glcm.npy
data/baseline/lung2_gldm.npy
data/baseline/lung2_glrlm.npy
data/baseline/lung2_glszm.npy
data/baseline/lung2_ngtdm.npy
data/baseline/wavelet.npy
pyradiomics_cuda.egg-info/PKG-INFO
pyradiomics_cuda.egg-info/SOURCES.txt
pyradiomics_cuda.egg-info/dependency_links.txt
pyradiomics_cuda.egg-info/entry_points.txt
pyradiomics_cuda.egg-info/not-zip-safe
pyradiomics_cuda.egg-info/requires.txt
pyradiomics_cuda.egg-info/top_level.txt
