Metadata-Version: 2.4
Name: pyradiomics-cuda
Version: 1.0.1
Summary: CUDA-accelerated fork of PyRadiomics - a Radiomics features library for python
Author-email: Piotr Tyrakowski <verscup@gmail.com>, Jakub Lisowski <Jlisowskyy@gmail.com>, PyRadiomics Community <pyradiomics@googlegroups.com>
License: Copyright 2023-2024 Piotr Tyrakowski, Jakub Lisowski - CUDA extensions and modifications
Project-URL: Homepage, https://github.com/PiotrTyrakowski/pyradiomics-CUDA
Project-URL: Original PyRadiomics, http://github.com/AIM-Harvard/pyradiomics#readme
Project-URL: Radiomics.io, https://www.radiomics.io/
Project-URL: Documentation, https://pyradiomics.readthedocs.io/en/latest/index.html
Project-URL: Docker, https://hub.docker.com/r/radiomics/pyradiomics/
Project-URL: Github, https://github.com/AIM-Harvard/pyradiomics
Keywords: radiomics,cancerimaging,medicalresearch,computationalimaging,cuda,gpu
Classifier: Development Status :: 4 - Beta
Classifier: Environment :: Console
Classifier: Intended Audience :: Developers
Classifier: Intended Audience :: Science/Research
Classifier: Operating System :: OS Independent
Classifier: Programming Language :: C
Classifier: Programming Language :: Python :: 3.5
Classifier: Programming Language :: Python :: 3.6
Classifier: Programming Language :: Python :: 3.7
Classifier: Programming Language :: Python :: 3.8
Classifier: Programming Language :: Python :: 3.9
Classifier: Topic :: Scientific/Engineering :: Bio-Informatics
Requires-Python: >=3.5
License-File: LICENSE.txt
Requires-Dist: numpy
Requires-Dist: SimpleITK
Requires-Dist: PyWavelets
Requires-Dist: pykwalify
Requires-Dist: six
Dynamic: license-file
